{
    "time_entries": [
        {
            "start_time": {
                "date": "20.12.2022",
                "time": "20:08:46"
            },
            "end_time": {
                "date": "30.12.2022",
                "time": "20:08:46"
            }
        },
        {
            "start_time": {
                "date": "20.12.2022",
                "time": "20:12:32"
            },
            "end_time": {
                "date": "20.12.2022",
                "time": "20:12:33"
            }
        },
        {
            "start_time": {
                "date": "20.12.2022",
                "time": "20:14:12"
            },
            "end_time": {
                "date": "20.12.2022",
                "time": "20:14:12"
            }
        },
        {
            "start_time": {
                "date": "20.12.2022",
                "time": "20:14:13"
            },
            "end_time": {
                "date": "20.12.2022",
                "time": "20:14:13"
            }
        },
        {
            "start_time": {
                "date": "20.12.2022",
                "time": "20:14:44"
            },
            "end_time": {
                "date": "20.12.2022",
                "time": "20:14:44"
            }
        },
        {
            "start_time": {
                "date": "20.12.2022",
                "time": "20:14:46"
            },
            "end_time": {
                "date": "20.12.2022",
                "time": "20:14:46"
            }
        },
        {
            "start_time": {
                "date": "20.12.2022",
                "time": "20:14:59"
            },
            "end_time": {
                "date": "20.12.2022",
                "time": "20:14:59"
            }
        },
        {
            "start_time": {
                "date": "20.12.2022",
                "time": "20:15:00"
            },
            "end_time": {
                "date": "20.12.2022",
                "time": "20:15:00"
            }
        },
        {
            "start_time": {
                "date": "20.12.2022",
                "time": "20:15:04"
            },
            "end_time": {
                "date": "20.12.2022",
                "time": "20:15:05"
            }
        },
        {
            "start_time": {
                "date": "20.12.2022",
                "time": "20:15:53"
            },
            "end_time": {
                "date": "20.12.2022",
                "time": "20:15:53"
            }
        },
        {
            "start_time": {
                "date": "20.12.2022",
                "time": "20:15:54"
            },
            "end_time": {
                "date": "20.12.2022",
                "time": "20:15:55"
            }
        },
        {
            "start_time": {
                "date": "20.12.2022",
                "time": "20:15:56"
            },
            "end_time": {
                "date": "20.12.2022",
                "time": "20:15:56"
            }
        },
        {
            "start_time": {
                "date": "20.12.2022",
                "time": "20:15:57"
            },
            "end_time": {
                "date": "20.12.2022",
                "time": "20:15:57"
            }
        },
        {
            "start_time": {
                "date": "20.12.2022",
                "time": "20:16:07"
            },
            "end_time": {
                "date": "20.12.2022",
                "time": "20:16:08"
            }
        },
        {
            "start_time": {
                "date": "20.12.2022",
                "time": "20:16:09"
            },
            "end_time": {
                "date": "20.12.2022",
                "time": "20:16:09"
            }
        },
        {
            "start_time": {
                "date": "20.12.2022",
                "time": "20:17:31"
            },
            "end_time": {
                "date": "20.12.2022",
                "time": "20:17:32"
            }
        },
        {
            "start_time": {
                "date": "20.12.2022",
                "time": "20:17:32"
            },
            "end_time": {
                "date": "20.12.2022",
                "time": "20:17:33"
            }
        },
        {
            "start_time": {
                "date": "20.12.2022",
                "time": "20:17:33"
            },
            "end_time": {
                "date": "20.12.2022",
                "time": "20:17:34"
            }
        },
        {
            "start_time": {
                "date": "20.12.2022",
                "time": "20:17:34"
            },
            "end_time": {
                "date": "20.12.2022",
                "time": "20:17:35"
            }
        },
        {
            "start_time": {
                "date": "20.12.2022",
                "time": "20:17:35"
            },
            "end_time": {
                "date": "20.12.2022",
                "time": "20:17:36"
            }
        },
        {
            "start_time": {
                "date": "20.12.2022",
                "time": "20:17:36"
            },
            "end_time": {
                "date": "20.12.2022",
                "time": "20:17:37"
            }
        },
        {
            "start_time": {
                "date": "20.12.2022",
                "time": "20:17:48"
            },
            "end_time": {
                "date": "20.12.2022",
                "time": "20:17:49"
            }
        },
        {
            "start_time": {
                "date": "20.12.2022",
                "time": "20:17:57"
            },
            "end_time": {
                "date": "20.12.2022",
                "time": "20:17:57"
            }
        },
        {
            "start_time": {
                "date": "20.12.2022",
                "time": "20:18:01"
            },
            "end_time": {
                "date": "20.12.2022",
                "time": "20:18:01"
            }
        },
        {
            "start_time": {
                "date": "20.12.2022",
                "time": "20:18:02"
            },
            "end_time": {
                "date": "20.12.2022",
                "time": "20:18:02"
            }
        },
        {
            "start_time": {
                "date": "20.12.2022",
                "time": "20:18:05"
            },
            "end_time": {
                "date": "20.12.2022",
                "time": "20:20:43"
            }
        },
        {
            "start_time": {
                "date": "20.12.2022",
                "time": "20:27:56"
            },
            "end_time": {
                "date": "20.12.2022",
                "time": "20:27:56"
            }
        },
        {
            "start_time": {
                "date": "20.12.2022",
                "time": "20:27:58"
            },
            "end_time": {
                "date": "20.12.2022",
                "time": "20:27:58"
            }
        },
        {
            "start_time": {
                "date": "20.12.2022",
                "time": "20:27:59"
            },
            "end_time": {
                "date": "20.12.2022",
                "time": "20:28:00"
            }
        },
        {
            "start_time": {
                "date": "20.12.2022",
                "time": "20:34:31"
            },
            "end_time": {
                "date": "20.12.2022",
                "time": "20:34:32"
            }
        },
        {
            "start_time": {
                "date": "20.12.2022",
                "time": "20:41:46"
            },
            "end_time": {
                "date": "20.12.2022",
                "time": "20:41:46"
            }
        },
        {
            "start_time": {
                "date": "20.12.2022",
                "time": "20:46:35"
            },
            "end_time": {
                "date": "20.12.2022",
                "time": "20:46:36"
            }
        },
        {
            "start_time": {
                "date": "20.12.2022",
                "time": "21:03:04"
            },
            "end_time": {
                "date": "20.12.2022",
                "time": "21:03:05"
            }
        },
        {
            "start_time": {
                "date": "20.12.2022",
                "time": "21:03:06"
            },
            "end_time": {
                "date": "20.12.2022",
                "time": "21:03:07"
            }
        },
        {
            "start_time": {
                "date": "20.12.2022",
                "time": "21:03:09"
            },
            "end_time": {
                "date": "20.12.2022",
                "time": "21:03:10"
            }
        },
        {
            "start_time": {
                "date": "20.12.2022",
                "time": "21:03:11"
            },
            "end_time": {
                "date": "20.12.2022",
                "time": "21:03:12"
            }
        },
        {
            "start_time": {
                "date": "20.12.2022",
                "time": "21:03:22"
            },
            "end_time": {
                "date": "20.12.2022",
                "time": "21:03:22"
            }
        },
        {
            "start_time": {
                "date": "20.12.2022",
                "time": "21:03:23"
            },
            "end_time": {
                "date": "20.12.2022",
                "time": "21:03:23"
            }
        },
        {
            "start_time": {
                "date": "20.12.2022",
                "time": "21:04:18"
            },
            "end_time": {
                "date": "20.12.2022",
                "time": "21:04:19"
            }
        },
        {
            "start_time": {
                "date": "20.12.2022",
                "time": "21:04:20"
            },
            "end_time": {
                "date": "20.12.2022",
                "time": "21:04:20"
            }
        },
        {
            "start_time": {
                "date": "20.12.2022",
                "time": "21:06:01"
            },
            "end_time": {
                "date": "20.12.2022",
                "time": "21:06:01"
            }
        },
        {
            "start_time": {
                "date": "20.12.2022",
                "time": "21:07:30"
            },
            "end_time": {
                "date": "20.12.2022",
                "time": "21:07:31"
            }
        },
        {
            "start_time": {
                "date": "20.12.2022",
                "time": "21:12:19"
            },
            "end_time": {
                "date": "20.12.2022",
                "time": "21:12:20"
            }
        },
        {
            "start_time": {
                "date": "20.12.2022",
                "time": "21:12:36"
            },
            "end_time": {
                "date": "20.12.2022",
                "time": "21:12:45"
            }
        },
        {
            "start_time": {
                "date": "20.12.2022",
                "time": "21:16:58"
            },
            "end_time": {
                "date": "20.12.2022",
                "time": "21:16:59"
            }
        },
        {
            "start_time": {
                "date": "20.12.2022",
                "time": "21:17:00"
            },
            "end_time": {
                "date": "20.12.2022",
                "time": "21:17:09"
            }
        },
        {
            "start_time": {
                "date": "20.12.2022",
                "time": "21:17:58"
            },
            "end_time": {
                "date": "20.12.2022",
                "time": "21:18:03"
            }
        },
        {
            "start_time": {
                "date": "20.12.2022",
                "time": "21:20:42"
            },
            "end_time": {
                "date": "20.12.2022",
                "time": "21:20:43"
            }
        },
        {
            "start_time": {
                "date": "20.12.2022",
                "time": "21:20:44"
            },
            "end_time": {
                "date": "20.12.2022",
                "time": "21:20:50"
            }
        },
        {
            "start_time": {
                "date": "20.12.2022",
                "time": "21:25:38"
            },
            "end_time": null
        },
        {
            "start_time": {
                "date": "20.12.2022",
                "time": "21:38:46"
            },
            "end_time": {
                "date": "20.12.2022",
                "time": "21:38:53"
            }
        },
        {
            "start_time": {
                "date": "20.12.2022",
                "time": "21:39:37"
            },
            "end_time": {
                "date": "20.12.2022",
                "time": "21:39:38"
            }
        },
        {
            "start_time": {
                "date": "20.12.2022",
                "time": "21:39:39"
            },
            "end_time": {
                "date": "20.12.2022",
                "time": "21:39:39"
            }
        },
        {
            "start_time": {
                "date": "20.12.2022",
                "time": "21:41:50"
            },
            "end_time": {
                "date": "20.12.2022",
                "time": "21:41:57"
            }
        },
        {
            "start_time": {
                "date": "20.12.2022",
                "time": "21:42:48"
            },
            "end_time": {
                "date": "20.12.2022",
                "time": "21:42:49"
            }
        },
        {
            "start_time": {
                "date": "20.12.2022",
                "time": "21:42:49"
            },
            "end_time": {
                "date": "20.12.2022",
                "time": "21:42:50"
            }
        },
        {
            "start_time": {
                "date": "20.12.2022",
                "time": "21:42:51"
            },
            "end_time": {
                "date": "20.12.2022",
                "time": "21:43:02"
            }
        },
        {
            "start_time": {
                "date": "20.12.2022",
                "time": "21:43:04"
            },
            "end_time": {
                "date": "20.12.2022",
                "time": "21:43:16"
            }
        },
        {
            "start_time": {
                "date": "20.12.2022",
                "time": "21:46:27"
            },
            "end_time": {
                "date": "20.12.2022",
                "time": "21:46:29"
            }
        },
        {
            "start_time": {
                "date": "20.12.2022",
                "time": "21:46:35"
            },
            "end_time": {
                "date": "20.12.2022",
                "time": "21:46:42"
            }
        },
        {
            "start_time": {
                "date": "20.12.2022",
                "time": "21:46:43"
            },
            "end_time": null
        },
        {
            "start_time": {
                "date": "20.12.2022",
                "time": "21:47:30"
            },
            "end_time": {
                "date": "20.12.2022",
                "time": "21:47:31"
            }
        },
        {
            "start_time": {
                "date": "20.12.2022",
                "time": "21:47:33"
            },
            "end_time": {
                "date": "20.12.2022",
                "time": "21:47:33"
            }
        },
        {
            "start_time": {
                "date": "20.12.2022",
                "time": "21:47:34"
            },
            "end_time": {
                "date": "20.12.2022",
                "time": "21:47:34"
            }
        },
        {
            "start_time": {
                "date": "20.12.2022",
                "time": "21:48:54"
            },
            "end_time": {
                "date": "20.12.2022",
                "time": "21:48:59"
            }
        },
        {
            "start_time": {
                "date": "20.12.2022",
                "time": "21:49:00"
            },
            "end_time": {
                "date": "20.12.2022",
                "time": "21:49:01"
            }
        },
        {
            "start_time": {
                "date": "20.12.2022",
                "time": "21:49:02"
            },
            "end_time": {
                "date": "20.12.2022",
                "time": "21:49:02"
            }
        },
        {
            "start_time": {
                "date": "20.12.2022",
                "time": "21:50:08"
            },
            "end_time": {
                "date": "20.12.2022",
                "time": "21:50:08"
            }
        },
        {
            "start_time": {
                "date": "20.12.2022",
                "time": "21:51:29"
            },
            "end_time": {
                "date": "20.12.2022",
                "time": "21:51:29"
            }
        },
        {
            "start_time": {
                "date": "20.12.2022",
                "time": "21:51:30"
            },
            "end_time": {
                "date": "20.12.2022",
                "time": "21:51:30"
            }
        },
        {
            "start_time": {
                "date": "20.12.2022",
                "time": "21:57:29"
            },
            "end_time": {
                "date": "20.12.2022",
                "time": "21:57:29"
            }
        },
        {
            "start_time": {
                "date": "20.12.2022",
                "time": "21:57:30"
            },
            "end_time": {
                "date": "20.12.2022",
                "time": "21:57:37"
            }
        },
        {
            "start_time": {
                "date": "20.12.2022",
                "time": "22:02:08"
            },
            "end_time": null
        },
        {
            "start_time": {
                "date": "20.12.2022",
                "time": "22:05:08"
            },
            "end_time": {
                "date": "20.12.2022",
                "time": "22:05:14"
            }
        },
        {
            "start_time": {
                "date": "20.12.2022",
                "time": "22:09:20"
            },
            "end_time": {
                "date": "20.12.2022",
                "time": "22:09:39"
            }
        },
        {
            "start_time": {
                "date": "20.12.2022",
                "time": "22:59:36"
            },
            "end_time": {
                "date": "20.12.2022",
                "time": "22:59:36"
            }
        },
        {
            "start_time": {
                "date": "20.12.2022",
                "time": "22:59:37"
            },
            "end_time": {
                "date": "20.12.2022",
                "time": "22:59:38"
            }
        },
        {
            "start_time": {
                "date": "20.12.2022",
                "time": "22:59:38"
            },
            "end_time": {
                "date": "20.12.2022",
                "time": "22:59:39"
            }
        },
        {
            "start_time": {
                "date": "20.12.2022",
                "time": "22:59:40"
            },
            "end_time": {
                "date": "20.12.2022",
                "time": "22:59:40"
            }
        },
        {
            "start_time": {
                "date": "20.12.2022",
                "time": "22:59:55"
            },
            "end_time": {
                "date": "20.12.2022",
                "time": "23:00:03"
            }
        },
        {
            "start_time": {
                "date": "20.12.2022",
                "time": "23:00:07"
            },
            "end_time": {
                "date": "20.12.2022",
                "time": "23:00:08"
            }
        },
        {
            "start_time": {
                "date": "21.12.2022",
                "time": "00:07:32"
            },
            "end_time": {
                "date": "21.12.2022",
                "time": "00:07:33"
            }
        },
        {
            "start_time": {
                "date": "21.12.2022",
                "time": "00:07:33"
            },
            "end_time": {
                "date": "21.12.2022",
                "time": "00:07:34"
            }
        },
        {
            "start_time": {
                "date": "21.12.2022",
                "time": "00:07:35"
            },
            "end_time": {
                "date": "21.12.2022",
                "time": "00:07:35"
            }
        },
        {
            "start_time": {
                "date": "21.12.2022",
                "time": "00:07:41"
            },
            "end_time": {
                "date": "21.12.2022",
                "time": "00:07:42"
            }
        },
        {
            "start_time": {
                "date": "21.12.2022",
                "time": "00:07:42"
            },
            "end_time": {
                "date": "21.12.2022",
                "time": "00:07:42"
            }
        },
        {
            "start_time": {
                "date": "21.12.2022",
                "time": "00:08:00"
            },
            "end_time": {
                "date": "21.12.2022",
                "time": "00:08:01"
            }
        },
        {
            "start_time": {
                "date": "21.12.2022",
                "time": "00:08:02"
            },
            "end_time": {
                "date": "21.12.2022",
                "time": "00:08:03"
            }
        },
        {
            "start_time": {
                "date": "21.12.2022",
                "time": "00:20:26"
            },
            "end_time": {
                "date": "21.12.2022",
                "time": "00:20:28"
            }
        },
        {
            "start_time": {
                "date": "21.12.2022",
                "time": "00:20:28"
            },
            "end_time": {
                "date": "21.12.2022",
                "time": "00:20:29"
            }
        },
        {
            "start_time": {
                "date": "21.12.2022",
                "time": "00:20:29"
            },
            "end_time": {
                "date": "21.12.2022",
                "time": "00:20:30"
            }
        },
        {
            "start_time": {
                "date": "21.12.2022",
                "time": "00:20:51"
            },
            "end_time": {
                "date": "21.12.2022",
                "time": "00:20:51"
            }
        },
        {
            "start_time": {
                "date": "21.12.2022",
                "time": "00:20:52"
            },
            "end_time": {
                "date": "21.12.2022",
                "time": "00:20:53"
            }
        },
        {
            "start_time": {
                "date": "21.12.2022",
                "time": "00:40:47"
            },
            "end_time": {
                "date": "21.12.2022",
                "time": "00:40:47"
            }
        },
        {
            "start_time": {
                "date": "21.12.2022",
                "time": "00:40:48"
            },
            "end_time": {
                "date": "21.12.2022",
                "time": "00:40:49"
            }
        },
        {
            "start_time": {
                "date": "21.12.2022",
                "time": "00:40:49"
            },
            "end_time": {
                "date": "21.12.2022",
                "time": "00:40:50"
            }
        },
        {
            "start_time": {
                "date": "21.12.2022",
                "time": "00:40:50"
            },
            "end_time": {
                "date": "21.12.2022",
                "time": "00:40:51"
            }
        },
        {
            "start_time": {
                "date": "21.12.2022",
                "time": "00:40:51"
            },
            "end_time": null
        },
        {
            "start_time": {
                "date": "21.12.2022",
                "time": "00:46:03"
            },
            "end_time": {
                "date": "21.12.2022",
                "time": "00:46:04"
            }
        },
        {
            "start_time": {
                "date": "21.12.2022",
                "time": "00:46:05"
            },
            "end_time": {
                "date": "21.12.2022",
                "time": "00:46:05"
            }
        },
        {
            "start_time": {
                "date": "21.12.2022",
                "time": "00:46:06"
            },
            "end_time": {
                "date": "21.12.2022",
                "time": "00:46:06"
            }
        },
        {
            "start_time": {
                "date": "21.12.2022",
                "time": "00:46:07"
            },
            "end_time": {
                "date": "21.12.2022",
                "time": "00:46:08"
            }
        },
        {
            "start_time": {
                "date": "21.12.2022",
                "time": "00:46:09"
            },
            "end_time": {
                "date": "21.12.2022",
                "time": "00:46:09"
            }
        },
        {
            "start_time": {
                "date": "21.12.2022",
                "time": "00:46:10"
            },
            "end_time": {
                "date": "21.12.2022",
                "time": "00:46:11"
            }
        },
        {
            "start_time": {
                "date": "21.12.2022",
                "time": "00:46:11"
            },
            "end_time": {
                "date": "21.12.2022",
                "time": "00:46:12"
            }
        },
        {
            "start_time": {
                "date": "21.12.2022",
                "time": "00:46:12"
            },
            "end_time": {
                "date": "21.12.2022",
                "time": "00:46:13"
            }
        },
        {
            "start_time": {
                "date": "21.12.2022",
                "time": "00:46:13"
            },
            "end_time": {
                "date": "21.12.2022",
                "time": "00:46:14"
            }
        },
        {
            "start_time": {
                "date": "21.12.2022",
                "time": "00:46:14"
            },
            "end_time": {
                "date": "21.12.2022",
                "time": "00:46:14"
            }
        },
        {
            "start_time": {
                "date": "21.12.2022",
                "time": "00:46:15"
            },
            "end_time": {
                "date": "21.12.2022",
                "time": "00:46:15"
            }
        },
        {
            "start_time": {
                "date": "21.12.2022",
                "time": "00:46:16"
            },
            "end_time": {
                "date": "21.12.2022",
                "time": "00:46:16"
            }
        },
        {
            "start_time": {
                "date": "21.12.2022",
                "time": "00:46:17"
            },
            "end_time": {
                "date": "21.12.2022",
                "time": "00:46:21"
            }
        },
        {
            "start_time": {
                "date": "21.12.2022",
                "time": "00:49:41"
            },
            "end_time": {
                "date": "21.12.2022",
                "time": "00:49:41"
            }
        },
        {
            "start_time": {
                "date": "21.12.2022",
                "time": "00:49:42"
            },
            "end_time": {
                "date": "21.12.2022",
                "time": "00:49:42"
            }
        },
        {
            "start_time": {
                "date": "21.12.2022",
                "time": "00:55:48"
            },
            "end_time": {
                "date": "21.12.2022",
                "time": "00:55:48"
            }
        },
        {
            "start_time": {
                "date": "21.12.2022",
                "time": "00:55:49"
            },
            "end_time": {
                "date": "21.12.2022",
                "time": "00:55:49"
            }
        },
        {
            "start_time": {
                "date": "21.12.2022",
                "time": "00:56:25"
            },
            "end_time": {
                "date": "21.12.2022",
                "time": "00:56:26"
            }
        }
    ]
}